socialfeeder/__init__.py
socialfeeder/__main__.py
socialfeeder/feeder.py
socialfeeder/engines/__init__.py
socialfeeder/engines/core.py
socialfeeder/engines/facebook.py
socialfeeder/utilities/__init__.py
socialfeeder/utilities/common.py
socialfeeder/utilities/configuration.py
socialfeeder/utilities/configuration.xsd
socialfeeder/utilities/constants.py
socialfeeder-1.1.1.dist-info/LICENSE
socialfeeder-1.1.1.dist-info/METADATA
socialfeeder-1.1.1.dist-info/WHEEL
socialfeeder-1.1.1.dist-info/entry_points.txt
socialfeeder-1.1.1.dist-info/top_level.txt
socialfeeder-1.1.1.dist-info/RECORD
