Metadata-Version: 2.1
Name: socialfeeder
Version: 1.1.1
Summary: A package to feed things on social
Home-page: https://github.com/datnguye
Author: datnguye
Author-email: datnguyen.it09@gmail.com
License: MIT
Platform: UNKNOWN
Requires-Python: >=3.7.5
Requires-Dist: selenium (==3.141.0)
Requires-Dist: webdriver-manager (==2.5.3)
Requires-Dist: beautifulsoup4 (==4.9.1)
Requires-Dist: lxml (==4.6.1)
